{
    "name": "wen",
    "host": "ghc51.ghc.andrew.cmu.edu",
    "protocol": "sftp",
    "port": 22,
    "username": "yunwenw",
    "password": "Hh65251741_/?",
    "remotePath": "/afs/andrew.cmu.edu/usr6/yunwenw/private/15642/scotty/src",
    "uploadOnSave": false,
    "downloadOnOpen": false,
    "watcher": {
        "files": "**/*",
        "autoUpload": true,
        "autoDelete": true
    },
    "ignore": [
        ".vscode",
        ".git",
        ".idea",
        ".DS_Store",
        "admin"
    ]
}

